changcheon_dong/__init__.py
changcheon_dong/agents.py
changcheon_dong/interfaces/__init__.py
changcheon_dong/interfaces/llamacpp.py
changcheon_dong/interfaces/messages.py
changcheon_dong/interfaces/models.py
changcheon_dong/models/__init__.py
changcheon_dong/models/base.py
changcheon_dong/models/hermes.py
changcheon_dong/models/mistral.py
changcheon_dong/models/models.py
changcheon_dong/utils.py
changcheon_dong-0.0.18.dist-info/METADATA
changcheon_dong-0.0.18.dist-info/WHEEL
changcheon_dong-0.0.18.dist-info/RECORD
